smbmap/__init__.py
smbmap/smbmap.py
smbmap-1.10.8.dist-info/licenses/LICENSE
smbmap-1.10.8.dist-info/METADATA
smbmap-1.10.8.dist-info/WHEEL
smbmap-1.10.8.dist-info/entry_points.txt
smbmap-1.10.8.dist-info/top_level.txt
smbmap-1.10.8.dist-info/RECORD
