Metadata-Version: 2.4
Name: smbmap
Version: 1.10.8
Summary:  SMBMap is a handy SMB enumeration tool 
Home-page: https://github.com/ShawnDEvans/smbmap
Author: ShawnDEvans
Author-email: ShawnDEvans@gmail.com
Project-URL: Bug Tracker, https://github.com/ShawnDEvans/smbmap/issues?q=is%3Aissue+is%3Aopen+sort%3Aupdated-desc
Classifier: Programming Language :: Python :: 3
Classifier: License :: OSI Approved :: GNU General Public License v3 (GPLv3)
Classifier: Operating System :: OS Independent
Requires-Python: >=3.6
License-File: LICENSE
Requires-Dist: impacket
Requires-Dist: pyasn1
Requires-Dist: pycryptodome
Requires-Dist: configparser
Requires-Dist: termcolor
Dynamic: author
Dynamic: author-email
Dynamic: classifier
Dynamic: description
Dynamic: description-content-type
Dynamic: home-page
Dynamic: license-file
Dynamic: project-url
Dynamic: requires-dist
Dynamic: requires-python
Dynamic: summary
